sqlite2png.py
v140dev_sqlalchemy_schemadisplay.py
sqlite2png-1.1.4.dist-info/LICENSE.sqlalchemy_schemadisplay
sqlite2png-1.1.4.dist-info/METADATA
sqlite2png-1.1.4.dist-info/WHEEL
sqlite2png-1.1.4.dist-info/entry_points.txt
sqlite2png-1.1.4.dist-info/top_level.txt
sqlite2png-1.1.4.dist-info/RECORD
