Metadata-Version: 2.1
Name: sqlite2png
Version: 1.1.4
Summary: Command line tool to get a png diagram of SQLite DB
Author-email: Anatoli Babenia <anatoli@rainforce.org>
Project-URL: homepage, https://github.com/abitrolly/sqlite2png
Classifier: Development Status :: 5 - Production/Stable
Classifier: Intended Audience :: Developers
Classifier: Topic :: Database :: Front-Ends
Classifier: Operating System :: OS Independent
License-File: LICENSE.sqlalchemy_schemadisplay
Requires-Dist: sqlalchemy
Requires-Dist: pydot
